importurl/__init__.py
importurl/__init__.pyi
importurl/module.py
importurl/module.pyi
importurl-0.1.2.dist-info/LICENSE
importurl-0.1.2.dist-info/METADATA
importurl-0.1.2.dist-info/WHEEL
importurl-0.1.2.dist-info/top_level.txt
importurl-0.1.2.dist-info/RECORD
