Metadata-Version: 2.1
Name: importurl
Version: 0.1.2
Summary: Import python module using url with importurl
Author: VenzTechnolo
Author-email: venztechnolo@gmail.com
Keywords: import,module,url,requests
Classifier: Intended Audience :: Developers
Classifier: Programming Language :: Python :: 3
Classifier: Development Status :: 5 - Production/Stable
Requires: requests
License-File: LICENSE
